{
"meta":{"test_sets":[],"test_metrics":[],"learn_metrics":[{"best_value":"Min","name":"Logloss"}],"launch_mode":"Train","parameters":"","iteration_count":200,"learn_sets":["learn"],"name":"experiment"},
"iterations":[
{"learn":[0.6505339251],"iteration":0,"passed_time":0.05009941949,"remaining_time":9.969784478},
{"learn":[0.6060136266],"iteration":1,"passed_time":0.055022521,"remaining_time":5.447229579},
{"learn":[0.564401037],"iteration":2,"passed_time":0.05759303723,"remaining_time":3.781942778},
{"learn":[0.5287033508],"iteration":3,"passed_time":0.06026481967,"remaining_time":2.952976164},
{"learn":[0.5023996919],"iteration":4,"passed_time":0.06365082889,"remaining_time":2.482382327},
{"learn":[0.4843669533],"iteration":5,"passed_time":0.06692381602,"remaining_time":2.163870051},
{"learn":[0.4623809043],"iteration":6,"passed_time":0.06997885733,"remaining_time":1.929417066},
{"learn":[0.4526109399],"iteration":7,"passed_time":0.07836861704,"remaining_time":1.880846809},
{"learn":[0.4417280603],"iteration":8,"passed_time":0.08097363749,"remaining_time":1.718440529},
{"learn":[0.4297789664],"iteration":9,"passed_time":0.08323559604,"remaining_time":1.581476325},
{"learn":[0.4196073584],"iteration":10,"passed_time":0.08599849128,"remaining_time":1.477610441},
{"learn":[0.4113928673],"iteration":11,"passed_time":0.08892405839,"remaining_time":1.393143581},
{"learn":[0.4043107895],"iteration":12,"passed_time":0.09548140042,"remaining_time":1.373463221},
{"learn":[0.3975681334],"iteration":13,"passed_time":0.09960540692,"remaining_time":1.323328978},
{"learn":[0.3866831087],"iteration":14,"passed_time":0.1027981406,"remaining_time":1.267843734},
{"learn":[0.3794809838],"iteration":15,"passed_time":0.1053059335,"remaining_time":1.211018235},
{"learn":[0.3748848658],"iteration":16,"passed_time":0.1133595798,"remaining_time":1.220282535},
{"learn":[0.3725212233],"iteration":17,"passed_time":0.1185013558,"remaining_time":1.198180375},
{"learn":[0.3668827042],"iteration":18,"passed_time":0.1205111181,"remaining_time":1.148026967},
{"learn":[0.3583401458],"iteration":19,"passed_time":0.1241447464,"remaining_time":1.117302717},
{"learn":[0.3524579083],"iteration":20,"passed_time":0.1280972296,"remaining_time":1.091876385},
{"learn":[0.3477992874],"iteration":21,"passed_time":0.1392480382,"remaining_time":1.126643218},
{"learn":[0.3440598071],"iteration":22,"passed_time":0.1464960705,"remaining_time":1.127382803},
{"learn":[0.342756377],"iteration":23,"passed_time":0.1485602073,"remaining_time":1.08944152},
{"learn":[0.3387288922],"iteration":24,"passed_time":0.158606545,"remaining_time":1.110245815},
{"learn":[0.3345312863],"iteration":25,"passed_time":0.1602606563,"remaining_time":1.072513623},
{"learn":[0.3304329457],"iteration":26,"passed_time":0.1632031347,"remaining_time":1.045708974},
{"learn":[0.3251845396],"iteration":27,"passed_time":0.1664919808,"remaining_time":1.022736454},
{"learn":[0.3222632054],"iteration":28,"passed_time":0.1681675488,"remaining_time":0.9916086497},
{"learn":[0.3173287722],"iteration":29,"passed_time":0.1725951625,"remaining_time":0.9780392543},
{"learn":[0.3147629936],"iteration":30,"passed_time":0.1759978743,"remaining_time":0.9594722826},
{"learn":[0.3124218732],"iteration":31,"passed_time":0.1781782556,"remaining_time":0.9354358417},
{"learn":[0.3103282761],"iteration":32,"passed_time":0.1810361051,"remaining_time":0.9161524105},
{"learn":[0.3072596113],"iteration":33,"passed_time":0.1860913926,"remaining_time":0.9085638581},
{"learn":[0.3045296355],"iteration":34,"passed_time":0.1911533137,"remaining_time":0.9011513359},
{"learn":[0.3025879786],"iteration":35,"passed_time":0.1952245547,"remaining_time":0.8893563048},
{"learn":[0.2975490931],"iteration":36,"passed_time":0.2011059598,"remaining_time":0.8859532825},
{"learn":[0.2943242067],"iteration":37,"passed_time":0.20581098,"remaining_time":0.877404704},
{"learn":[0.2908633246],"iteration":38,"passed_time":0.2104380133,"remaining_time":0.8687312858},
{"learn":[0.2894565937],"iteration":39,"passed_time":0.2144041277,"remaining_time":0.8576165107},
{"learn":[0.2877378125],"iteration":40,"passed_time":0.2191717525,"remaining_time":0.8499587476},
{"learn":[0.284500464],"iteration":41,"passed_time":0.2232240172,"remaining_time":0.8397474935},
{"learn":[0.2823056101],"iteration":42,"passed_time":0.2296123544,"remaining_time":0.8383520846},
{"learn":[0.2797987769],"iteration":43,"passed_time":0.2375865309,"remaining_time":0.842352246},
{"learn":[0.2767399427],"iteration":44,"passed_time":0.2414543959,"remaining_time":0.8316762527},
{"learn":[0.2719917454],"iteration":45,"passed_time":0.2454849973,"remaining_time":0.8218410779},
{"learn":[0.2696468093],"iteration":46,"passed_time":0.2478177953,"remaining_time":0.8067260146},
{"learn":[0.2654716147],"iteration":47,"passed_time":0.2595296443,"remaining_time":0.8218438737},
{"learn":[0.2632550537],"iteration":48,"passed_time":0.2664094248,"remaining_time":0.8209759826},
{"learn":[0.2610317773],"iteration":49,"passed_time":0.268337013,"remaining_time":0.8050110389},
{"learn":[0.257770746],"iteration":50,"passed_time":0.2707383528,"remaining_time":0.7909806777},
{"learn":[0.2555443373],"iteration":51,"passed_time":0.2728384401,"remaining_time":0.7765401755},
{"learn":[0.254006398],"iteration":52,"passed_time":0.2757504529,"remaining_time":0.7648172939},
{"learn":[0.2515479577],"iteration":53,"passed_time":0.2777812697,"remaining_time":0.7510382478},
{"learn":[0.2489745624],"iteration":54,"passed_time":0.2796222912,"remaining_time":0.7371860406},
{"learn":[0.2474440383],"iteration":55,"passed_time":0.2821070175,"remaining_time":0.725418045},
{"learn":[0.2462791854],"iteration":56,"passed_time":0.2842701378,"remaining_time":0.7131689421},
{"learn":[0.2439552477],"iteration":57,"passed_time":0.2864565342,"remaining_time":0.7013246181},
{"learn":[0.2403891334],"iteration":58,"passed_time":0.2884841241,"remaining_time":0.689428161},
{"learn":[0.2369465822],"iteration":59,"passed_time":0.2903349866,"remaining_time":0.677448302},
{"learn":[0.2344864109],"iteration":60,"passed_time":0.2924662595,"remaining_time":0.6664395093},
{"learn":[0.23276295],"iteration":61,"passed_time":0.2953454355,"remaining_time":0.6573817757},
{"learn":[0.2301005128],"iteration":62,"passed_time":0.2969883269,"remaining_time":0.6458317586},
{"learn":[0.2283035544],"iteration":63,"passed_time":0.2987037525,"remaining_time":0.6347454741},
{"learn":[0.2277311216],"iteration":64,"passed_time":0.3004825483,"remaining_time":0.6240791388},
{"learn":[0.2251464107],"iteration":65,"passed_time":0.3019786046,"remaining_time":0.613108076},
{"learn":[0.2225585239],"iteration":66,"passed_time":0.3037139385,"remaining_time":0.6028948332},
{"learn":[0.2206113722],"iteration":67,"passed_time":0.3053221034,"remaining_time":0.5926840831},
{"learn":[0.2188536326],"iteration":68,"passed_time":0.3072736179,"remaining_time":0.5833745499},
{"learn":[0.2123748716],"iteration":69,"passed_time":0.311159366,"remaining_time":0.5778673939},
{"learn":[0.2089578847],"iteration":70,"passed_time":0.3135073521,"remaining_time":0.5696119497},
{"learn":[0.2057669686],"iteration":71,"passed_time":0.3162933851,"remaining_time":0.5622993512},
{"learn":[0.2035957427],"iteration":72,"passed_time":0.3198693045,"remaining_time":0.5564849544},
{"learn":[0.2022370786],"iteration":73,"passed_time":0.3235938765,"remaining_time":0.5509841681},
{"learn":[0.2003609055],"iteration":74,"passed_time":0.3264011855,"remaining_time":0.5440019758},
{"learn":[0.1984471251],"iteration":75,"passed_time":0.3294592478,"remaining_time":0.5375387728},
{"learn":[0.1960509054],"iteration":76,"passed_time":0.3325368097,"remaining_time":0.5311951636},
{"learn":[0.1937572776],"iteration":77,"passed_time":0.3368192114,"remaining_time":0.5268197922},
{"learn":[0.1923163399],"iteration":78,"passed_time":0.3405711949,"remaining_time":0.5216343618},
{"learn":[0.1902288854],"iteration":79,"passed_time":0.3448718806,"remaining_time":0.5173078208},
{"learn":[0.1878512585],"iteration":80,"passed_time":0.3474547098,"remaining_time":0.510458154},
{"learn":[0.1854981498],"iteration":81,"passed_time":0.3496475322,"remaining_time":0.5031513269},
{"learn":[0.1830234771],"iteration":82,"passed_time":0.3529911485,"remaining_time":0.4975899322},
{"learn":[0.1827141818],"iteration":83,"passed_time":0.3551225846,"remaining_time":0.4904073788},
{"learn":[0.1788824226],"iteration":84,"passed_time":0.3574366895,"remaining_time":0.4835908152},
{"learn":[0.1765509219],"iteration":85,"passed_time":0.3603025447,"remaining_time":0.47761035},
{"learn":[0.1757857899],"iteration":86,"passed_time":0.3623829522,"remaining_time":0.4706813058},
{"learn":[0.1708289064],"iteration":87,"passed_time":0.3645259347,"remaining_time":0.4639420987},
{"learn":[0.1684850391],"iteration":88,"passed_time":0.3669094894,"remaining_time":0.4576062172},
{"learn":[0.1659800249],"iteration":89,"passed_time":0.381035157,"remaining_time":0.4657096364},
{"learn":[0.1622013507],"iteration":90,"passed_time":0.3863626397,"remaining_time":0.462786019},
{"learn":[0.1604362589],"iteration":91,"passed_time":0.3906740797,"remaining_time":0.458617398},
{"learn":[0.1585688396],"iteration":92,"passed_time":0.4117204027,"remaining_time":0.4736998181},
{"learn":[0.1568473134],"iteration":93,"passed_time":0.4157789529,"remaining_time":0.4688571171},
{"learn":[0.1547398811],"iteration":94,"passed_time":0.4181126743,"remaining_time":0.4621245347},
{"learn":[0.1537229583],"iteration":95,"passed_time":0.4200378188,"remaining_time":0.4550409704},
{"learn":[0.1515267203],"iteration":96,"passed_time":0.4237443805,"remaining_time":0.4499553731},
{"learn":[0.1493843374],"iteration":97,"passed_time":0.438865879,"remaining_time":0.456778772},
{"learn":[0.1481474194],"iteration":98,"passed_time":0.4425707931,"remaining_time":0.4515116172},
{"learn":[0.145376453],"iteration":99,"passed_time":0.4489240933,"remaining_time":0.4489240933},
{"learn":[0.144127939],"iteration":100,"passed_time":0.4524589523,"remaining_time":0.4434993691},
{"learn":[0.1434207806],"iteration":101,"passed_time":0.4796280623,"remaining_time":0.4608191186},
{"learn":[0.1417433684],"iteration":102,"passed_time":0.4865417303,"remaining_time":0.4581994936},
{"learn":[0.1400490148],"iteration":103,"passed_time":0.4979156187,"remaining_time":0.4596144173},
{"learn":[0.1385744586],"iteration":104,"passed_time":0.5025102881,"remaining_time":0.4546521654},
{"learn":[0.1354203651],"iteration":105,"passed_time":0.5160751691,"remaining_time":0.457651565},
{"learn":[0.1344179067],"iteration":106,"passed_time":0.5298488047,"remaining_time":0.4605227929},
{"learn":[0.1324512017],"iteration":107,"passed_time":0.5349393289,"remaining_time":0.4556890579},
{"learn":[0.1302751764],"iteration":108,"passed_time":0.5410664555,"remaining_time":0.4517160317},
{"learn":[0.1280879837],"iteration":109,"passed_time":0.5593833086,"remaining_time":0.4576772525},
{"learn":[0.1278374059],"iteration":110,"passed_time":0.5654737933,"remaining_time":0.4533979063},
{"learn":[0.1248903255],"iteration":111,"passed_time":0.5805803669,"remaining_time":0.4561702883},
{"learn":[0.1245927971],"iteration":112,"passed_time":0.5881985485,"remaining_time":0.4528608294},
{"learn":[0.1242238925],"iteration":113,"passed_time":0.5962918859,"remaining_time":0.4498342297},
{"learn":[0.1234041056],"iteration":114,"passed_time":0.6026480305,"remaining_time":0.4454355008},
{"learn":[0.1218192545],"iteration":115,"passed_time":0.6311330192,"remaining_time":0.4570273588},
{"learn":[0.1211197886],"iteration":116,"passed_time":0.6474051421,"remaining_time":0.4592703145},
{"learn":[0.1188418552],"iteration":117,"passed_time":0.6646825925,"remaining_time":0.4618980727},
{"learn":[0.1185063914],"iteration":118,"passed_time":0.6809281454,"remaining_time":0.4634889057},
{"learn":[0.1174070851],"iteration":119,"passed_time":0.6953603201,"remaining_time":0.4635735467},
{"learn":[0.1157378606],"iteration":120,"passed_time":0.7067683738,"remaining_time":0.4614438143},
{"learn":[0.1143621314],"iteration":121,"passed_time":0.7092091095,"remaining_time":0.4534287749},
{"learn":[0.1129332656],"iteration":122,"passed_time":0.7111425062,"remaining_time":0.4451867722},
{"learn":[0.1124490727],"iteration":123,"passed_time":0.7291021045,"remaining_time":0.4468690318},
{"learn":[0.1123822778],"iteration":124,"passed_time":0.7566314572,"remaining_time":0.4539788743},
{"learn":[0.111002515],"iteration":125,"passed_time":0.7609125821,"remaining_time":0.4468851673},
{"learn":[0.1102933794],"iteration":126,"passed_time":0.7647391805,"remaining_time":0.4395744896},
{"learn":[0.1075835621],"iteration":127,"passed_time":0.7726216122,"remaining_time":0.4345996569},
{"learn":[0.1051984097],"iteration":128,"passed_time":0.7746963472,"remaining_time":0.4263832609},
{"learn":[0.104297098],"iteration":129,"passed_time":0.7780094532,"remaining_time":0.4189281671},
{"learn":[0.1039360289],"iteration":130,"passed_time":0.7807677704,"remaining_time":0.4112440928},
{"learn":[0.10193049],"iteration":131,"passed_time":0.7827947553,"remaining_time":0.4032579042},
{"learn":[0.1008071524],"iteration":132,"passed_time":0.7850511599,"remaining_time":0.3954769001},
{"learn":[0.1002095612],"iteration":133,"passed_time":0.7872910158,"remaining_time":0.3877702018},
{"learn":[0.09942663009],"iteration":134,"passed_time":0.790802823,"remaining_time":0.3807569148},
{"learn":[0.09823961442],"iteration":135,"passed_time":0.7971956812,"remaining_time":0.3751509088},
{"learn":[0.09601439465],"iteration":136,"passed_time":0.8063621058,"remaining_time":0.3708088516},
{"learn":[0.09470515959],"iteration":137,"passed_time":0.8147422424,"remaining_time":0.3660436162},
{"learn":[0.09353683189],"iteration":138,"passed_time":0.8308574494,"remaining_time":0.3646208951},
{"learn":[0.09195655078],"iteration":139,"passed_time":0.8365328667,"remaining_time":0.3585140857},
{"learn":[0.09177004587],"iteration":140,"passed_time":0.8436405357,"remaining_time":0.3530127064},
{"learn":[0.09052793734],"iteration":141,"passed_time":0.8473525318,"remaining_time":0.3461017383},
{"learn":[0.08879529564],"iteration":142,"passed_time":0.8586362754,"remaining_time":0.3422536203},
{"learn":[0.08745136743],"iteration":143,"passed_time":0.8608043985,"remaining_time":0.3347572661},
{"learn":[0.08646545679],"iteration":144,"passed_time":0.8647060229,"remaining_time":0.3279919397},
{"learn":[0.08505629985],"iteration":145,"passed_time":0.8684000095,"remaining_time":0.3211890446},
{"learn":[0.08481602978],"iteration":146,"passed_time":0.870280446,"remaining_time":0.3137745826},
{"learn":[0.08349293118],"iteration":147,"passed_time":0.8720132012,"remaining_time":0.3063830166},
{"learn":[0.0828355221],"iteration":148,"passed_time":0.8740033693,"remaining_time":0.2991555157},
{"learn":[0.08237051876],"iteration":149,"passed_time":0.8798831843,"remaining_time":0.2932943948},
{"learn":[0.08147950528],"iteration":150,"passed_time":0.8825081677,"remaining_time":0.2863768226},
{"learn":[0.08024198092],"iteration":151,"passed_time":0.8856892344,"remaining_time":0.2796913372},
{"learn":[0.08006945427],"iteration":152,"passed_time":0.8910300692,"remaining_time":0.2737151193},
{"learn":[0.07919410819],"iteration":153,"passed_time":0.8961145101,"remaining_time":0.2676705679},
{"learn":[0.07797188868],"iteration":154,"passed_time":0.9025045596,"remaining_time":0.2620174528},
{"learn":[0.07735978513],"iteration":155,"passed_time":0.9085595778,"remaining_time":0.2562603937},
{"learn":[0.07640488356],"iteration":156,"passed_time":0.9174053256,"remaining_time":0.251263879},
{"learn":[0.07563812088],"iteration":157,"passed_time":0.9262506055,"remaining_time":0.2462185154},
{"learn":[0.07471709946],"iteration":158,"passed_time":0.9378294633,"remaining_time":0.241830239},
{"learn":[0.07431617962],"iteration":159,"passed_time":0.942283683,"remaining_time":0.2355709207},
{"learn":[0.07384528302],"iteration":160,"passed_time":0.9443605272,"remaining_time":0.2287581401},
{"learn":[0.07303807047],"iteration":161,"passed_time":0.9504170904,"remaining_time":0.2229373422},
{"learn":[0.07218228327],"iteration":162,"passed_time":0.9544578283,"remaining_time":0.2166560714},
{"learn":[0.07128082852],"iteration":163,"passed_time":0.9568013398,"remaining_time":0.2100295624},
{"learn":[0.07078865839],"iteration":164,"passed_time":0.9614927279,"remaining_time":0.2039530029},
{"learn":[0.07058058847],"iteration":165,"passed_time":0.9647240644,"remaining_time":0.1975940855},
{"learn":[0.06951790991],"iteration":166,"passed_time":0.9685508739,"remaining_time":0.1913902925},
{"learn":[0.06921651354],"iteration":167,"passed_time":0.97064951,"remaining_time":0.184885621},
{"learn":[0.0683232136],"iteration":168,"passed_time":0.9736209057,"remaining_time":0.1785931839},
{"learn":[0.06753564598],"iteration":169,"passed_time":0.9777816753,"remaining_time":0.1725497074},
{"learn":[0.06690180446],"iteration":170,"passed_time":0.9806127254,"remaining_time":0.1663027429},
{"learn":[0.06637711136],"iteration":171,"passed_time":0.9829620925,"remaining_time":0.1600170848},
{"learn":[0.06570317078],"iteration":172,"passed_time":0.9883932106,"remaining_time":0.1542578999},
{"learn":[0.06560022871],"iteration":173,"passed_time":0.995940306,"remaining_time":0.1488186664},
{"learn":[0.06486177032],"iteration":174,"passed_time":1.00090119,"remaining_time":0.1429858843},
{"learn":[0.0646390742],"iteration":175,"passed_time":1.004973787,"remaining_time":0.13704188},
{"learn":[0.0642070918],"iteration":176,"passed_time":1.00850779,"remaining_time":0.1310490348},
{"learn":[0.063552844],"iteration":177,"passed_time":1.016052296,"remaining_time":0.1255794973},
{"learn":[0.06351937592],"iteration":178,"passed_time":1.02044869,"remaining_time":0.1197174441},
{"learn":[0.06256314137],"iteration":179,"passed_time":1.026233005,"remaining_time":0.1140258894},
{"learn":[0.06216775389],"iteration":180,"passed_time":1.034081375,"remaining_time":0.1085499786},
{"learn":[0.06168112816],"iteration":181,"passed_time":1.03805623,"remaining_time":0.1026649018},
{"learn":[0.06138006986],"iteration":182,"passed_time":1.040403019,"remaining_time":0.09664946076},
{"learn":[0.06102142455],"iteration":183,"passed_time":1.044902435,"remaining_time":0.09086108128},
{"learn":[0.06087271871],"iteration":184,"passed_time":1.048771608,"remaining_time":0.08503553577},
{"learn":[0.06080814661],"iteration":185,"passed_time":1.053313527,"remaining_time":0.07928166336},
{"learn":[0.06021188206],"iteration":186,"passed_time":1.056310093,"remaining_time":0.07343332196},
{"learn":[0.05957609154],"iteration":187,"passed_time":1.060978647,"remaining_time":0.0677220413},
{"learn":[0.05955715834],"iteration":188,"passed_time":1.064819018,"remaining_time":0.06197359366},
{"learn":[0.05866809346],"iteration":189,"passed_time":1.068463479,"remaining_time":0.05623491995},
{"learn":[0.05775477817],"iteration":190,"passed_time":1.074794655,"remaining_time":0.05064477432},
{"learn":[0.05680431925],"iteration":191,"passed_time":1.077093912,"remaining_time":0.04487891301},
{"learn":[0.05652111151],"iteration":192,"passed_time":1.079509156,"remaining_time":0.03915318181},
{"learn":[0.05632925731],"iteration":193,"passed_time":1.081202793,"remaining_time":0.03343926165},
{"learn":[0.0559943778],"iteration":194,"passed_time":1.082767444,"remaining_time":0.02776326779},
{"learn":[0.05544642469],"iteration":195,"passed_time":1.084319354,"remaining_time":0.0221289664},
{"learn":[0.05541677265],"iteration":196,"passed_time":1.087321664,"remaining_time":0.01655819793},
{"learn":[0.05512141809],"iteration":197,"passed_time":1.09173143,"remaining_time":0.0110275902},
{"learn":[0.05460524754],"iteration":198,"passed_time":1.095447885,"remaining_time":0.00550476324},
{"learn":[0.05395219616],"iteration":199,"passed_time":1.09822126,"remaining_time":0}
]}